Metadata-Version: 2.1
Name: PyPDF2-Fields
Version: 1.0.0
Summary: Library PyPDF2_Fields is a complement to PyPDF2. It helps using a PDF file’s fields by facilitating several tasks.
Home-page: https://github.com/GRV96/PyPDF2_Fields
Author: Guyllaume Rousseau
License: MIT
Platform: UNKNOWN
Classifier: Development Status :: 5 - Production/Stable
Classifier: Intended Audience :: Developers
Classifier: License :: OSI Approved :: MIT License
Classifier: Operating System :: OS Independent
Classifier: Programming Language :: Python :: 3
Classifier: Topic :: Software Development :: Libraries :: Python Modules
Classifier: Topic :: Utilities
License-File: LICENSE
